protonoc/__init__.py
protonoc/main.py
protonoc/run_modes.py
protonoc/simulator/__init__.py
protonoc/simulator/entities.py
protonoc/simulator/extra.py
protonoc/simulator/model.py
protonoc/simulator/utils.py
protonoc/simulator/inputs/eindhoven/data/conviction_length.csv
protonoc/simulator/inputs/eindhoven/data/crime_rate_by_gender_and_age.csv
protonoc/simulator/inputs/eindhoven/data/crime_rate_by_gender_and_age_range.csv
protonoc/simulator/inputs/eindhoven/data/employer_sizes.csv
protonoc/simulator/inputs/eindhoven/data/head_age_dist_by_household_size.csv
protonoc/simulator/inputs/eindhoven/data/household_size_dist.csv
protonoc/simulator/inputs/eindhoven/data/household_type_dist_by_age.csv
protonoc/simulator/inputs/eindhoven/data/initial_age_gender_dist.csv
protonoc/simulator/inputs/eindhoven/data/initial_fertility_rates.csv
protonoc/simulator/inputs/eindhoven/data/initial_mortality_rates.csv
protonoc/simulator/inputs/eindhoven/data/labour_status.csv
protonoc/simulator/inputs/eindhoven/data/labour_status_range.csv
protonoc/simulator/inputs/eindhoven/data/proportion_of_male_singles_by_age.csv
protonoc/simulator/inputs/eindhoven/data/proportion_single_fathers.csv
protonoc/simulator/inputs/general/data/marriages_stats.csv
protonoc/simulator/inputs/general/data/num_co_offenders_dist.csv
protonoc/simulator/inputs/palermo/data/children_age_dist.csv
protonoc/simulator/inputs/palermo/data/conviction_length.csv
protonoc/simulator/inputs/palermo/data/crime_rate_by_gender_and_age.csv
protonoc/simulator/inputs/palermo/data/crime_rate_by_gender_and_age_range.csv
protonoc/simulator/inputs/palermo/data/edu.csv
protonoc/simulator/inputs/palermo/data/edu_by_wealth_lvl.csv
protonoc/simulator/inputs/palermo/data/employer_sizes.csv
protonoc/simulator/inputs/palermo/data/head_age_dist_by_household_size.csv
protonoc/simulator/inputs/palermo/data/household_size_dist.csv
protonoc/simulator/inputs/palermo/data/household_type_dist_by_age.csv
protonoc-1.0.dist-info/LICENSE.txt
protonoc-1.0.dist-info/METADATA
protonoc-1.0.dist-info/WHEEL
protonoc-1.0.dist-info/entry_points.txt
protonoc-1.0.dist-info/top_level.txt
protonoc-1.0.dist-info/RECORD
