Metadata-Version: 2.1
Name: protonoc
Version: 1.0
Summary: Simulation of recruitment to terrorism. Developed by LABSS-CNR for the PROTON project, https://www.projectproton.eu
Home-page: https://github.com/LABSS/PyPROTON-OC
Author: LABSS(Francesco Mattioli, Mario Paolucci)
Author-email: francesco@nientepanico.org, mario.paolucci@istc.cnr.it
License: UNKNOWN
Platform: UNKNOWN
Classifier: Development Status :: 5 - Production/Stable
Classifier: Programming Language :: Python :: 3.8
Classifier: Programming Language :: Python :: 3.9
Classifier: Topic :: Scientific/Engineering :: Artificial Life
Classifier: Topic :: Sociology
Classifier: License :: OSI Approved :: MIT License
Requires-Python: >=3.8
Requires-Dist: click (>=7.1.2)
Requires-Dist: networkx (>=2.5)
Requires-Dist: numpy (>=1.20)
Requires-Dist: pandas (>=1.1.4)
Requires-Dist: tornado (>=6.1)
Requires-Dist: tqdm (>=4.53)
Requires-Dist: numba (>=0.51.2)
Requires-Dist: psutil (>=5.8.0)
Requires-Dist: mesa (>=0.8.8)
Requires-Dist: prettytable (>=2.1)
